dj_mongoengine_rql/__init__.py
dj_mongoengine_rql/constants.py
dj_mongoengine_rql/filter_cls.py
dj_mongoengine_rql/q.py
django_mongoengine_rql-0.2.2.dist-info/LICENSE
django_mongoengine_rql-0.2.2.dist-info/METADATA
django_mongoengine_rql-0.2.2.dist-info/WHEEL
django_mongoengine_rql-0.2.2.dist-info/RECORD
