Metadata-Version: 2.1
Name: django-mongoengine-rql
Version: 0.2.2
Summary: Django Mongoengine RQL Filtering
Home-page: https://connect.cloudblue.com/community/api/rql/
License: Apache-2.0
Keywords: rql,filter,django,mongo,mongoengine
Author: Ingram Micro
Requires-Python: >=3.8,<4.0
Classifier: Development Status :: 3 - Alpha
Classifier: Framework :: Django :: 3.2
Classifier: Framework :: Django :: 4.1
Classifier: Framework :: Django :: 4.2
Classifier: Intended Audience :: Developers
Classifier: License :: OSI Approved :: Apache Software License
Classifier: Operating System :: Unix
Classifier: Programming Language :: Python :: 3
Classifier: Programming Language :: Python :: 3.8
Classifier: Programming Language :: Python :: 3.9
Classifier: Programming Language :: Python :: 3.10
Classifier: Programming Language :: Python :: 3.11
Classifier: Topic :: Text Processing :: Filters
Requires-Dist: django-mongoengine (>=0.5.4,<0.6.0)
Requires-Dist: django-rql (>=4.2.0,<5.0.0)
Project-URL: Repository, https://github.com/cloudblue/django-mongoengine-rql
